aegisml/__init__.py
aegisml/dataset.py
aegisml/downloader.py
aegisml/manager.py
aegisml-4.0.dist-info/METADATA
aegisml-4.0.dist-info/WHEEL
aegisml-4.0.dist-info/top_level.txt
aegisml-4.0.dist-info/RECORD
